{
  "best_metric": null,
  "best_model_checkpoint": null,
  "epoch": 4.0,
  "eval_steps": 500,
  "global_step": 176,
  "is_hyper_param_search": false,
  "is_local_process_zero": true,
  "is_world_process_zero": true,
  "log_history": [
    {
      "epoch": 1.0,
      "eval_loss": 1.3600064516067505,
      "eval_runtime": 17.756,
      "eval_samples_per_second": 4.843,
      "eval_steps_per_second": 0.62,
      "step": 44
    },
    {
      "epoch": 1.1389290882778582,
      "grad_norm": 7.723332405090332,
      "learning_rate": 1.5348837209302328e-05,
      "loss": 1.4499,
      "step": 50
    },
    {
      "epoch": 2.0,
      "eval_loss": 1.1944539546966553,
      "eval_runtime": 16.274,
      "eval_samples_per_second": 5.285,
      "eval_steps_per_second": 0.676,
      "step": 88
    },
    {
      "epoch": 2.2778581765557164,
      "grad_norm": 9.763964653015137,
      "learning_rate": 1.0697674418604651e-05,
      "loss": 1.2087,
      "step": 100
    },
    {
      "epoch": 3.0,
      "eval_loss": 1.081748127937317,
      "eval_runtime": 16.3153,
      "eval_samples_per_second": 5.271,
      "eval_steps_per_second": 0.674,
      "step": 132
    },
    {
      "epoch": 3.4167872648335744,
      "grad_norm": 4.89656400680542,
      "learning_rate": 6.046511627906977e-06,
      "loss": 1.0739,
      "step": 150
    },
    {
      "epoch": 4.0,
      "eval_loss": 1.0170944929122925,
      "eval_runtime": 16.0429,
      "eval_samples_per_second": 5.361,
      "eval_steps_per_second": 0.686,
      "step": 176
    }
  ],
  "logging_steps": 50,
  "max_steps": 215,
  "num_input_tokens_seen": 0,
  "num_train_epochs": 5,
  "save_steps": 500,
  "stateful_callbacks": {
    "TrainerControl": {
      "args": {
        "should_epoch_stop": false,
        "should_evaluate": false,
        "should_log": false,
        "should_save": true,
        "should_training_stop": false
      },
      "attributes": {}
    }
  },
  "total_flos": 1.2664480311803904e+17,
  "train_batch_size": 2,
  "trial_name": null,
  "trial_params": null
}
